streamlit_tile_grid/DonutRenderer.py
streamlit_tile_grid/TileRenderer.py
streamlit_tile_grid/__init__.py
streamlit_tile_grid-0.3.7.dist-info/METADATA
streamlit_tile_grid-0.3.7.dist-info/WHEEL
streamlit_tile_grid-0.3.7.dist-info/top_level.txt
streamlit_tile_grid-0.3.7.dist-info/RECORD
